diff2test/__init__.py
diff2test/ai_client.py
diff2test/cli_parser.py
diff2test/file_writer.py
diff2test/git_handler.py
diff2test/logger.py
diff2test/main.py
diff2test/models.py
diff2test/prompt_builder.py
diff2test/response_parser.py
diff2test/tests/__init__.py
diff2test/tests/test_ai_client.py
diff2test/tests/test_cli_parser.py
diff2test/tests/test_file_writer.py
diff2test/tests/test_git_handler.py
diff2test/tests/test_logger.py
diff2test/tests/test_prompt_builder.py
diff2test/tests/test_response_parser.py
diff2test/utils.py
diff2test-0.1.0.dist-info/LICENSE
diff2test-0.1.0.dist-info/METADATA
diff2test-0.1.0.dist-info/WHEEL
diff2test-0.1.0.dist-info/entry_points.txt
diff2test-0.1.0.dist-info/RECORD
