Metadata-Version: 2.3
Name: diff2test
Version: 0.1.0
Summary: AI-Powered Unit Test Generation from Git Diffs
Author: yoon-yoo-sang
Author-email: yyss6188@naver.com
Requires-Python: >=3.11
Classifier: Programming Language :: Python :: 3
Classifier: Programming Language :: Python :: 3.11
Classifier: Programming Language :: Python :: 3.12
Classifier: Programming Language :: Python :: 3.13
Requires-Dist: black (>=25.1.0,<26.0.0)
Requires-Dist: google-cloud-aiplatform (>=1.95.1,<2.0.0)
Requires-Dist: pytest (>=8.3.5,<9.0.0)
Requires-Dist: requests (>=2.32.3,<3.0.0)
Requires-Dist: rich (>=14.0.0,<15.0.0)
Requires-Dist: typer (>=0.16.0,<0.17.0)
